simple_chat_structure/__init__.py
simple_chat_structure/chat.py
tests/__init__.py
tests/test_chat.py
simple_chat_structure-0.1.2.dist-info/LICENSE
simple_chat_structure-0.1.2.dist-info/METADATA
simple_chat_structure-0.1.2.dist-info/WHEEL
simple_chat_structure-0.1.2.dist-info/top_level.txt
simple_chat_structure-0.1.2.dist-info/RECORD
