Metadata-Version: 2.2
Name: simple-chat-structure
Version: 0.1.2
Summary: Библиотека для управления структурой чатов и сообщений
Home-page: https://github.com/VKolebcev/simple_chat_structure
Author: Vladislav K
Author-email: vkolebcev@yandex.ru
Project-URL: Bug Tracker, https://github.com/VKolebcev/simple_chat_structure/issues
Classifier: Programming Language :: Python :: 3
Classifier: License :: OSI Approved :: MIT License
Classifier: Operating System :: OS Independent
Classifier: Topic :: Software Development :: Libraries
Classifier: Topic :: Communications :: Chat
Requires-Python: >=3.8
License-File: LICENSE
Dynamic: author
Dynamic: author-email
Dynamic: classifier
Dynamic: description
Dynamic: description-content-type
Dynamic: home-page
Dynamic: project-url
Dynamic: requires-python
Dynamic: summary
